json_to_clickhouse/__init__.py
json_to_clickhouse/json_to_clickhouse.py
json_to_clickhouse-0.1.20.dist-info/METADATA
json_to_clickhouse-0.1.20.dist-info/WHEEL
json_to_clickhouse-0.1.20.dist-info/RECORD
