Metadata-Version: 2.3
Name: json-to-clickhouse
Version: 0.1.20
Summary: 
Author: Vladimir Muzychenko
Author-email: vladimir.muzychenko@gmail.com
Requires-Python: >=3.8,<4.0
Classifier: Programming Language :: Python :: 3
Classifier: Programming Language :: Python :: 3.8
Classifier: Programming Language :: Python :: 3.9
Classifier: Programming Language :: Python :: 3.10
Classifier: Programming Language :: Python :: 3.11
Classifier: Programming Language :: Python :: 3.12
Classifier: Programming Language :: Python :: 3.13
Requires-Dist: clickhouse-connect (>=0.8.15,<0.9.0)
